cargo_mcp/__init__.py
cargo_mcp/server.py
cargo_mcp-0.1.0.dist-info/METADATA
cargo_mcp-0.1.0.dist-info/WHEEL
cargo_mcp-0.1.0.dist-info/entry_points.txt
cargo_mcp-0.1.0.dist-info/licenses/LICENSE
cargo_mcp-0.1.0.dist-info/RECORD
